examples/__init__.py
examples/create_model_configuration.py
pyflowline/__init__.py
pyflowline/algorithms/__init__.py
pyflowline/algorithms/auxiliary/__init__.py
pyflowline/algorithms/auxiliary/calculate_area_of_difference.py
pyflowline/algorithms/auxiliary/check_head_water.py
pyflowline/algorithms/auxiliary/find_index_in_list.py
pyflowline/algorithms/auxiliary/find_vertex_in_list.py
pyflowline/algorithms/connection/__init__.py
pyflowline/algorithms/connection/connect_disconnect_flowline.py
pyflowline/algorithms/cython/__init__.py
pyflowline/algorithms/cython/setup.py
pyflowline/algorithms/direction/__init__.py
pyflowline/algorithms/direction/correct_flowline_direction.py
pyflowline/algorithms/index/__init__.py
pyflowline/algorithms/index/define_stream_order.py
pyflowline/algorithms/index/define_stream_segment_index.py
pyflowline/algorithms/index/define_stream_topology.py
pyflowline/algorithms/intersect/__init__.py
pyflowline/algorithms/intersect/intersect_flowline_with_flowline.py
pyflowline/algorithms/intersect/intersect_flowline_with_mesh.py
pyflowline/algorithms/intersect/intersect_flowline_with_vertex.py
pyflowline/algorithms/loop/__init__.py
pyflowline/algorithms/loop/remove_flowline_loop.py
pyflowline/algorithms/merge/__init__.py
pyflowline/algorithms/merge/merge_flowline.py
pyflowline/algorithms/simplification/__init__.py
pyflowline/algorithms/simplification/remove_duplicate_edge.py
pyflowline/algorithms/simplification/remove_duplicate_flowline.py
pyflowline/algorithms/simplification/remove_returning_flowline.py
pyflowline/algorithms/simplification/remove_small_river.py
pyflowline/algorithms/split/__init__.py
pyflowline/algorithms/split/find_flowline_confluence.py
pyflowline/algorithms/split/find_flowline_vertex.py
pyflowline/algorithms/split/split_by_length.py
pyflowline/algorithms/split/split_flowline.py
pyflowline/algorithms/split/split_flowline_to_edge.py
pyflowline/classes/__init__.py
pyflowline/classes/_hpc.py
pyflowline/classes/_visual.py
pyflowline-0.3.10.dist-info/AUTHORS.rst
pyflowline-0.3.10.dist-info/LICENSE
pyflowline-0.3.10.dist-info/METADATA
pyflowline-0.3.10.dist-info/WHEEL
pyflowline-0.3.10.dist-info/top_level.txt
pyflowline-0.3.10.dist-info/RECORD
